ical2notion/__init__.py
ical2notion-0.3.1.dist-info/LICENSE
ical2notion-0.3.1.dist-info/METADATA
ical2notion-0.3.1.dist-info/WHEEL
ical2notion-0.3.1.dist-info/entry_points.txt
ical2notion-0.3.1.dist-info/top_level.txt
ical2notion-0.3.1.dist-info/RECORD
